household_env/__init__.py
household_env/colors_house_objects.json
household_env/dummy.py
household_env/house_objects.json
household_env/manual_control.py
household_env/operability.json
household_env/envs/__init__.py
household_env/envs/house_env.py
householdenv-0.0.3.dist-info/LICENSE
householdenv-0.0.3.dist-info/METADATA
householdenv-0.0.3.dist-info/WHEEL
householdenv-0.0.3.dist-info/top_level.txt
householdenv-0.0.3.dist-info/RECORD
