Metadata-Version: 2.1
Name: householdenv
Version: 0.0.3
Summary: This is an environment for RL purposes
Home-page: https://github.com/mrcabo/Household-env.git
Author: Diego Cabo Golvano
Author-email: dcgdiego@gmail.com
License: UNKNOWN
Project-URL: Source Code, https://github.com/mrcabo/Household-env.git
Keywords: Reinforcement Learning environment
Platform: UNKNOWN
Classifier: Programming Language :: Python :: 3
Classifier: License :: OSI Approved :: MIT License
Classifier: Operating System :: OS Independent
Requires-Dist: gym
Requires-Dist: numpy
